pkg_resources-stubs/METADATA.toml
pkg_resources-stubs/__init__.pyi
pkg_resources-stubs/py31compat.pyi
types_pkg_resources-0.1.3.dist-info/METADATA
types_pkg_resources-0.1.3.dist-info/WHEEL
types_pkg_resources-0.1.3.dist-info/top_level.txt
types_pkg_resources-0.1.3.dist-info/RECORD
